{
  "entry": "server.js",
  "files": {
    "components/answer-wait-post.js": "components/answer-wait-post.js",
    "components/answer-wait-reply.js": "components/answer-wait-reply.js",
    "components/filtered-post.js": "components/filtered-post.js",
    "components/new-post.js": "components/new-post.js",
    "components/shared-send-sentence.js": "components/shared-send-sentence.js",
    "pages/_id.js": "pages/_id.js",
    "pages/answer.js": "pages/answer.js",
    "pages/index.js": "pages/index.js",
    "server.js": "server.js"
  },
  "maps": {
    "components/answer-wait-post.js": "components/answer-wait-post.js.map",
    "components/answer-wait-reply.js": "components/answer-wait-reply.js.map",
    "components/filtered-post.js": "components/filtered-post.js.map",
    "components/new-post.js": "components/new-post.js.map",
    "components/shared-send-sentence.js": "components/shared-send-sentence.js.map",
    "pages/_id.js": "pages/_id.js.map",
    "pages/answer.js": "pages/answer.js.map",
    "pages/index.js": "pages/index.js.map",
    "server.js": "server.js.map"
  }
}